Metadata-Version: 1.1
Name: circlator
Version: 1.5.5
Summary: circlator: a tool to circularise genome assemblies
Home-page: https://github.com/sanger-pathogens/circlator
Author: Martin Hunt, Nishadi De Silva, (this small edit is from Nicola De Maio) 
Author-email: path-help@sanger.ac.uk
License: GPLv3
Platform: UNKNOWN
Classifier: Development Status :: 4 - Beta
Classifier: Topic :: Scientific/Engineering :: Bio-Informatics
Classifier: Programming Language :: Python :: 3 :: Only
Classifier: License :: OSI Approved :: GNU General Public License v3 (GPLv3)
